odoo8_addon_stock_inventory_line_price-8.0.1.0.0.99.dev10-py2.7-nspkg.pth
odoo8_addon_stock_inventory_line_price-8.0.1.0.0.99.dev10.dist-info/DESCRIPTION.rst
odoo8_addon_stock_inventory_line_price-8.0.1.0.0.99.dev10.dist-info/METADATA
odoo8_addon_stock_inventory_line_price-8.0.1.0.0.99.dev10.dist-info/RECORD
odoo8_addon_stock_inventory_line_price-8.0.1.0.0.99.dev10.dist-info/WHEEL
odoo8_addon_stock_inventory_line_price-8.0.1.0.0.99.dev10.dist-info/metadata.json
odoo8_addon_stock_inventory_line_price-8.0.1.0.0.99.dev10.dist-info/namespace_packages.txt
odoo8_addon_stock_inventory_line_price-8.0.1.0.0.99.dev10.dist-info/top_level.txt
odoo_addons/stock_inventory_line_price/README.rst
odoo_addons/stock_inventory_line_price/__init__.py
odoo_addons/stock_inventory_line_price/__openerp__.py
odoo_addons/stock_inventory_line_price/i18n/de.po
odoo_addons/stock_inventory_line_price/i18n/es.po
odoo_addons/stock_inventory_line_price/i18n/es_ES.po
odoo_addons/stock_inventory_line_price/i18n/fr.po
odoo_addons/stock_inventory_line_price/i18n/it.po
odoo_addons/stock_inventory_line_price/i18n/pt_BR.po
odoo_addons/stock_inventory_line_price/i18n/sk.po
odoo_addons/stock_inventory_line_price/i18n/sl.po
odoo_addons/stock_inventory_line_price/i18n/stock_inventory_line_price.pot
odoo_addons/stock_inventory_line_price/models/__init__.py
odoo_addons/stock_inventory_line_price/models/stock_inventory.py
odoo_addons/stock_inventory_line_price/tests/__init__.py
odoo_addons/stock_inventory_line_price/tests/test_stock_inventory_line_price.py
odoo_addons/stock_inventory_line_price/views/inventory_view.xml
