Metadata-Version: 2.0
Name: odoo8-addon-stock-inventory-line-price
Version: 8.0.1.0.0.99.dev10
Summary: Standard price at inventory level
Home-page: http://www.odoomrp.com
Author: OdooMRP team, AvanzOSC, Tecnativa, Odoo Community Association (OCA)
Author-email: support@odoo-community.org
License: UNKNOWN
Platform: UNKNOWN
Classifier: Programming Language :: Python
Classifier: Framework :: Odoo
Requires-Python: ~=2.7
Requires-Dist: odoo (<9.0a,>=8.0a)
